<annotation>
	<folder>pascal data</folder>
	<filename>70.png</filename>
	<path>C:\Users\Jackw\Documents\GitHub\openGL_floorplan\pascal data\70.png</path>
	<source>
		<database>Unknown</database>
	</source>
	<size>
		<width>268</width>
		<height>699</height>
		<depth>3</depth>
	</size>
	<segmented>0</segmented>
	<object>
		<name>door</name>
		<pose>Unspecified</pose>
		<truncated>0</truncated>
		<difficult>0</difficult>
		<bndbox>
			<xmin>20</xmin>
			<ymin>142</ymin>
			<xmax>55</xmax>
			<ymax>185</ymax>
		</bndbox>
	</object>
	<object>
		<name>door</name>
		<pose>Unspecified</pose>
		<truncated>0</truncated>
		<difficult>0</difficult>
		<bndbox>
			<xmin>54</xmin>
			<ymin>216</ymin>
			<xmax>97</xmax>
			<ymax>251</ymax>
		</bndbox>
	</object>
	<object>
		<name>door</name>
		<pose>Unspecified</pose>
		<truncated>0</truncated>
		<difficult>0</difficult>
		<bndbox>
			<xmin>59</xmin>
			<ymin>437</ymin>
			<xmax>95</xmax>
			<ymax>482</ymax>
		</bndbox>
	</object>
	<object>
		<name>door</name>
		<pose>Unspecified</pose>
		<truncated>0</truncated>
		<difficult>0</difficult>
		<bndbox>
			<xmin>102</xmin>
			<ymin>399</ymin>
			<xmax>139</xmax>
			<ymax>435</ymax>
		</bndbox>
	</object>
	<object>
		<name>toilet</name>
		<pose>Unspecified</pose>
		<truncated>0</truncated>
		<difficult>0</difficult>
		<bndbox>
			<xmin>126</xmin>
			<ymin>225</ymin>
			<xmax>157</xmax>
			<ymax>246</ymax>
		</bndbox>
	</object>
	<object>
		<name>basin</name>
		<pose>Unspecified</pose>
		<truncated>0</truncated>
		<difficult>0</difficult>
		<bndbox>
			<xmin>103</xmin>
			<ymin>252</ymin>
			<xmax>132</xmax>
			<ymax>273</ymax>
		</bndbox>
	</object>
	<object>
		<name>bathtub</name>
		<pose>Unspecified</pose>
		<truncated>0</truncated>
		<difficult>0</difficult>
		<bndbox>
			<xmin>87</xmin>
			<ymin>186</ymin>
			<xmax>154</xmax>
			<ymax>220</ymax>
		</bndbox>
	</object>
	<object>
		<name>stairs</name>
		<pose>Unspecified</pose>
		<truncated>0</truncated>
		<difficult>0</difficult>
		<bndbox>
			<xmin>60</xmin>
			<ymin>286</ymin>
			<xmax>94</xmax>
			<ymax>337</ymax>
		</bndbox>
	</object>
	<object>
		<name>stairs</name>
		<pose>Unspecified</pose>
		<truncated>0</truncated>
		<difficult>0</difficult>
		<bndbox>
			<xmin>18</xmin>
			<ymin>288</ymin>
			<xmax>53</xmax>
			<ymax>388</ymax>
		</bndbox>
	</object>
	<object>
		<name>window</name>
		<pose>Unspecified</pose>
		<truncated>0</truncated>
		<difficult>0</difficult>
		<bndbox>
			<xmin>177</xmin>
			<ymin>274</ymin>
			<xmax>211</xmax>
			<ymax>289</ymax>
		</bndbox>
	</object>
	<object>
		<name>window</name>
		<pose>Unspecified</pose>
		<truncated>0</truncated>
		<difficult>0</difficult>
		<bndbox>
			<xmin>54</xmin>
			<ymin>7</ymin>
			<xmax>99</xmax>
			<ymax>19</ymax>
		</bndbox>
	</object>
	<object>
		<name>window</name>
		<pose>Unspecified</pose>
		<truncated>0</truncated>
		<difficult>0</difficult>
		<bndbox>
			<xmin>30</xmin>
			<ymin>596</ymin>
			<xmax>80</xmax>
			<ymax>611</ymax>
		</bndbox>
	</object>
	<object>
		<name>window</name>
		<pose>Unspecified</pose>
		<truncated>0</truncated>
		<difficult>0</difficult>
		<bndbox>
			<xmin>128</xmin>
			<ymin>627</ymin>
			<xmax>181</xmax>
			<ymax>644</ymax>
		</bndbox>
	</object>
	<object>
		<name>window</name>
		<pose>Unspecified</pose>
		<truncated>0</truncated>
		<difficult>1</difficult>
		<bndbox>
			<xmin>185</xmin>
			<ymin>606</ymin>
			<xmax>213</xmax>
			<ymax>634</ymax>
		</bndbox>
	</object>
	<object>
		<name>window</name>
		<pose>Unspecified</pose>
		<truncated>0</truncated>
		<difficult>1</difficult>
		<bndbox>
			<xmin>95</xmin>
			<ymin>605</ymin>
			<xmax>124</xmax>
			<ymax>632</ymax>
		</bndbox>
	</object>
</annotation>
