<annotation>
	<folder>pascal data</folder>
	<filename>51.png</filename>
	<path>C:\Users\Jackw\Documents\GitHub\openGL_floorplan\pascal data\51.png</path>
	<source>
		<database>Unknown</database>
	</source>
	<size>
		<width>2480</width>
		<height>3508</height>
		<depth>1</depth>
	</size>
	<segmented>0</segmented>
	<object>
		<name>door</name>
		<pose>Unspecified</pose>
		<truncated>0</truncated>
		<difficult>0</difficult>
		<bndbox>
			<xmin>961</xmin>
			<ymin>1585</ymin>
			<xmax>1089</xmax>
			<ymax>1685</ymax>
		</bndbox>
	</object>
	<object>
		<name>door</name>
		<pose>Unspecified</pose>
		<truncated>0</truncated>
		<difficult>0</difficult>
		<bndbox>
			<xmin>824</xmin>
			<ymin>1737</ymin>
			<xmax>964</xmax>
			<ymax>1852</ymax>
		</bndbox>
	</object>
	<object>
		<name>door</name>
		<pose>Unspecified</pose>
		<truncated>0</truncated>
		<difficult>0</difficult>
		<bndbox>
			<xmin>1259</xmin>
			<ymin>1690</ymin>
			<xmax>1376</xmax>
			<ymax>1805</ymax>
		</bndbox>
	</object>
	<object>
		<name>door</name>
		<pose>Unspecified</pose>
		<truncated>0</truncated>
		<difficult>0</difficult>
		<bndbox>
			<xmin>1126</xmin>
			<ymin>1457</ymin>
			<xmax>1191</xmax>
			<ymax>1575</ymax>
		</bndbox>
	</object>
	<object>
		<name>door</name>
		<pose>Unspecified</pose>
		<truncated>0</truncated>
		<difficult>0</difficult>
		<bndbox>
			<xmin>1024</xmin>
			<ymin>992</ymin>
			<xmax>1136</xmax>
			<ymax>1100</ymax>
		</bndbox>
	</object>
	<object>
		<name>door</name>
		<pose>Unspecified</pose>
		<truncated>0</truncated>
		<difficult>0</difficult>
		<bndbox>
			<xmin>1286</xmin>
			<ymin>1110</ymin>
			<xmax>1396</xmax>
			<ymax>1217</ymax>
		</bndbox>
	</object>
	<object>
		<name>door</name>
		<pose>Unspecified</pose>
		<truncated>0</truncated>
		<difficult>0</difficult>
		<bndbox>
			<xmin>914</xmin>
			<ymin>1102</ymin>
			<xmax>1024</xmax>
			<ymax>1215</ymax>
		</bndbox>
	</object>
	<object>
		<name>toilet</name>
		<pose>Unspecified</pose>
		<truncated>0</truncated>
		<difficult>0</difficult>
		<bndbox>
			<xmin>1209</xmin>
			<ymin>1377</ymin>
			<xmax>1261</xmax>
			<ymax>1460</ymax>
		</bndbox>
	</object>
	<object>
		<name>stairs</name>
		<pose>Unspecified</pose>
		<truncated>0</truncated>
		<difficult>0</difficult>
		<bndbox>
			<xmin>1514</xmin>
			<ymin>1217</ymin>
			<xmax>1619</xmax>
			<ymax>1582</ymax>
		</bndbox>
	</object>
	<object>
		<name>window</name>
		<pose>Unspecified</pose>
		<truncated>0</truncated>
		<difficult>0</difficult>
		<bndbox>
			<xmin>609</xmin>
			<ymin>1377</ymin>
			<xmax>699</xmax>
			<ymax>1522</ymax>
		</bndbox>
	</object>
	<object>
		<name>window</name>
		<pose>Unspecified</pose>
		<truncated>0</truncated>
		<difficult>0</difficult>
		<bndbox>
			<xmin>611</xmin>
			<ymin>910</ymin>
			<xmax>689</xmax>
			<ymax>1060</ymax>
		</bndbox>
	</object>
	<object>
		<name>window</name>
		<pose>Unspecified</pose>
		<truncated>0</truncated>
		<difficult>0</difficult>
		<bndbox>
			<xmin>1086</xmin>
			<ymin>697</ymin>
			<xmax>1184</xmax>
			<ymax>805</ymax>
		</bndbox>
	</object>
	<object>
		<name>window</name>
		<pose>Unspecified</pose>
		<truncated>0</truncated>
		<difficult>0</difficult>
		<bndbox>
			<xmin>1589</xmin>
			<ymin>890</ymin>
			<xmax>1679</xmax>
			<ymax>1030</ymax>
		</bndbox>
	</object>
	<object>
		<name>window</name>
		<pose>Unspecified</pose>
		<truncated>0</truncated>
		<difficult>0</difficult>
		<bndbox>
			<xmin>496</xmin>
			<ymin>2120</ymin>
			<xmax>526</xmax>
			<ymax>2407</ymax>
		</bndbox>
	</object>
	<object>
		<name>window</name>
		<pose>Unspecified</pose>
		<truncated>0</truncated>
		<difficult>0</difficult>
		<bndbox>
			<xmin>701</xmin>
			<ymin>2465</ymin>
			<xmax>996</xmax>
			<ymax>2505</ymax>
		</bndbox>
	</object>
	<object>
		<name>window</name>
		<pose>Unspecified</pose>
		<truncated>0</truncated>
		<difficult>0</difficult>
		<bndbox>
			<xmin>1154</xmin>
			<ymin>2570</ymin>
			<xmax>1444</xmax>
			<ymax>2627</ymax>
		</bndbox>
	</object>
	<object>
		<name>window</name>
		<pose>Unspecified</pose>
		<truncated>0</truncated>
		<difficult>0</difficult>
		<bndbox>
			<xmin>1554</xmin>
			<ymin>2065</ymin>
			<xmax>1654</xmax>
			<ymax>2117</ymax>
		</bndbox>
	</object>
	<object>
		<name>window</name>
		<pose>Unspecified</pose>
		<truncated>0</truncated>
		<difficult>0</difficult>
		<bndbox>
			<xmin>1741</xmin>
			<ymin>1787</ymin>
			<xmax>1789</xmax>
			<ymax>1972</ymax>
		</bndbox>
	</object>
	<object>
		<name>window</name>
		<pose>Unspecified</pose>
		<truncated>0</truncated>
		<difficult>0</difficult>
		<bndbox>
			<xmin>1619</xmin>
			<ymin>1542</ymin>
			<xmax>1669</xmax>
			<ymax>1645</ymax>
		</bndbox>
	</object>
</annotation>
